cppark/__init__.py
cppark/main.py
cppark-0.0.3.dist-info/licenses/LICENSE
cppark-0.0.3.dist-info/METADATA
cppark-0.0.3.dist-info/WHEEL
cppark-0.0.3.dist-info/entry_points.txt
cppark-0.0.3.dist-info/top_level.txt
cppark-0.0.3.dist-info/RECORD
