Metadata-Version: 2.4
Name: cppark
Version: 0.0.3
Summary: Your C++ tools, all in one place.
Requires-Python: <4,>=3.10
License-File: LICENSE
Dynamic: license-file
